drf_orjson_rp/__init__.py
drf_orjson_rp/parsers.py
drf_orjson_rp/renderers.py
drf_orjson_rp-0.3.0.dist-info/METADATA
drf_orjson_rp-0.3.0.dist-info/WHEEL
drf_orjson_rp-0.3.0.dist-info/licenses/LICENSE
drf_orjson_rp-0.3.0.dist-info/RECORD
