Metadata-Version: 2.4
Name: drf-orjson-rp
Version: 0.3.0
Summary: DRF renderer and parser based on orjson
Project-URL: Repository, https://github.com/ArtemIsmagilov/drf_orjson_rp.git
License-Expression: MIT
License-File: LICENSE
Keywords: drf,orjson,parser,renderer
Classifier: Development Status :: 5 - Production/Stable
Classifier: Framework :: Django
Classifier: Intended Audience :: Developers
Classifier: License :: OSI Approved :: MIT License
Classifier: Operating System :: OS Independent
Classifier: Programming Language :: Python
Classifier: Programming Language :: Python :: 3
Classifier: Programming Language :: Python :: 3 :: Only
Classifier: Programming Language :: Python :: 3.9
Classifier: Programming Language :: Python :: 3.10
Classifier: Programming Language :: Python :: 3.11
Classifier: Programming Language :: Python :: 3.12
Classifier: Programming Language :: Python :: 3.13
Classifier: Programming Language :: Python :: Implementation :: CPython
Classifier: Topic :: Software Development :: Libraries :: Python Modules
Requires-Python: >=3.9
Requires-Dist: djangorestframework>=3.15.2
Requires-Dist: orjson>=3.10.15
